{
  "resolvedId": "/home/user/chakaralaya/Chakaralaya/node_modules/lucide-react/dist/esm/icons/arrow-big-right-dash.js",
  "transforms": [
    {
      "name": "vite:load-fallback",
      "result": "/**\n * @license lucide-react v0.552.0 - ISC\n *\n * This source code is licensed under the ISC license.\n * See the LICENSE file in the root directory of this source tree.\n */\n\nimport createLucideIcon from '../createLucideIcon.js';\n\nconst __iconNode = [\n  [\n    \"path\",\n    {\n      d: \"M11 9a1 1 0 0 0 1-1V5.061a1 1 0 0 1 1.811-.75l6.836 6.836a1.207 1.207 0 0 1 0 1.707l-6.836 6.835a1 1 0 0 1-1.811-.75V16a1 1 0 0 0-1-1H9a1 1 0 0 1-1-1v-4a1 1 0 0 1 1-1z\",\n      key: \"67vhrh\"\n    }\n  ],\n  [\"path\", { d: \"M4 9v6\", key: \"bns7oa\" }]\n];\nconst ArrowBigRightDash = createLucideIcon(\"arrow-big-right-dash\", __iconNode);\n\nexport { __iconNode, ArrowBigRightDash as default };\n//# sourceMappingURL=arrow-big-right-dash.js.map\n",
      "start": 1762100718702,
      "end": 1762100721156,
      "sourcemaps": null
    },
    {
      "name": "vite:esbuild",
      "start": 1762100721156,
      "end": 1762100721156,
      "order": "normal"
    },
    {
      "name": "vite:define",
      "start": 1762100721156,
      "end": 1762100721156,
      "order": "normal-normal"
    },
    {
      "name": "vite:reporter",
      "start": 1762100721156,
      "end": 1762100721156,
      "order": "normal"
    }
  ]
}
