{
  "resolvedId": "/home/user/chakaralaya/Chakaralaya/node_modules/motion-utils/dist/es/warn-once.mjs",
  "transforms": [
    {
      "name": "vite:load-fallback",
      "result": "import { formatErrorMessage } from './format-error-message.mjs';\n\nconst warned = new Set();\nfunction hasWarned(message) {\n    return warned.has(message);\n}\nfunction warnOnce(condition, message, errorCode) {\n    if (condition || warned.has(message))\n        return;\n    console.warn(formatErrorMessage(message, errorCode));\n    warned.add(message);\n}\n\nexport { hasWarned, warnOnce };\n",
      "start": 1762100729149,
      "end": 1762100729258,
      "sourcemaps": null
    },
    {
      "name": "vite:esbuild",
      "start": 1762100729259,
      "end": 1762100729259,
      "order": "normal"
    },
    {
      "name": "vite:define",
      "start": 1762100729259,
      "end": 1762100729259,
      "order": "normal-normal"
    },
    {
      "name": "vite:reporter",
      "start": 1762100729259,
      "end": 1762100729259,
      "order": "normal"
    }
  ]
}
