{
  "resolvedId": "/home/user/chakaralaya/Chakaralaya/node_modules/lucide-react/dist/esm/icons/square-arrow-out-down-right.js",
  "transforms": [
    {
      "name": "vite:load-fallback",
      "result": "/**\n * @license lucide-react v0.552.0 - ISC\n *\n * This source code is licensed under the ISC license.\n * See the LICENSE file in the root directory of this source tree.\n */\n\nimport createLucideIcon from '../createLucideIcon.js';\n\nconst __iconNode = [\n  [\"path\", { d: \"M21 11V5a2 2 0 0 0-2-2H5a2 2 0 0 0-2 2v14a2 2 0 0 0 2 2h6\", key: \"14rsvq\" }],\n  [\"path\", { d: \"m21 21-9-9\", key: \"1et2py\" }],\n  [\"path\", { d: \"M21 15v6h-6\", key: \"1jko0i\" }]\n];\nconst SquareArrowOutDownRight = createLucideIcon(\"square-arrow-out-down-right\", __iconNode);\n\nexport { __iconNode, SquareArrowOutDownRight as default };\n//# sourceMappingURL=square-arrow-out-down-right.js.map\n",
      "start": 1762100718699,
      "end": 1762100720940,
      "sourcemaps": null
    },
    {
      "name": "vite:esbuild",
      "start": 1762100720940,
      "end": 1762100720940,
      "order": "normal"
    },
    {
      "name": "vite:define",
      "start": 1762100720940,
      "end": 1762100720940,
      "order": "normal-normal"
    },
    {
      "name": "vite:reporter",
      "start": 1762100720940,
      "end": 1762100720940,
      "order": "normal"
    }
  ]
}
